odoo8_addon_stock_disable_force_availability_button-8.0.1.0.0.99.dev7-nspkg.pth
odoo_addons/stock_disable_force_availability_button/README.rst
odoo_addons/stock_disable_force_availability_button/__init__.py
odoo_addons/stock_disable_force_availability_button/__openerp__.py
odoo_addons/stock_disable_force_availability_button/i18n/de.po
odoo_addons/stock_disable_force_availability_button/i18n/fr.po
odoo_addons/stock_disable_force_availability_button/i18n/pt_BR.po
odoo_addons/stock_disable_force_availability_button/i18n/sl.po
odoo_addons/stock_disable_force_availability_button/i18n/stock_disable_force_availability_button.pot
odoo_addons/stock_disable_force_availability_button/security/stock_disable_force_availability_button_security.xml
odoo_addons/stock_disable_force_availability_button/static/description/icon.png
odoo_addons/stock_disable_force_availability_button/views/stock_view.xml
odoo8_addon_stock_disable_force_availability_button-8.0.1.0.0.99.dev7.dist-info/METADATA
odoo8_addon_stock_disable_force_availability_button-8.0.1.0.0.99.dev7.dist-info/WHEEL
odoo8_addon_stock_disable_force_availability_button-8.0.1.0.0.99.dev7.dist-info/namespace_packages.txt
odoo8_addon_stock_disable_force_availability_button-8.0.1.0.0.99.dev7.dist-info/top_level.txt
odoo8_addon_stock_disable_force_availability_button-8.0.1.0.0.99.dev7.dist-info/RECORD
